hashcash.py
hashcash-0.1.2.dist-info/METADATA
hashcash-0.1.2.dist-info/WHEEL
hashcash-0.1.2.dist-info/entry_points.txt
hashcash-0.1.2.dist-info/top_level.txt
hashcash-0.1.2.dist-info/RECORD
