Metadata-Version: 2.4
Name: hashcash
Version: 0.1.2
Summary: Hashcash
Author-email: David Mertz <unknown@invalid.tld>
Maintainer-email: Scott Alfter <scott@alfter.us>
Requires-Python: >=3.8
